legiaoalbuns.py
LegiaoUrbana-0.1.dist-info/LICENSE.txt
LegiaoUrbana-0.1.dist-info/METADATA
LegiaoUrbana-0.1.dist-info/WHEEL
LegiaoUrbana-0.1.dist-info/top_level.txt
LegiaoUrbana-0.1.dist-info/RECORD
